Workbook

Sheet AssetList
A1: App Name | B1: Department | C1: Vendor | D1: Fiscal Year | E1: Development Cost | F1: Sector
A2: Building Permit Processing System | B2: Department of Assets Information and Services | C2: Accenture Public Sector | D2: =-INT((RAND()^1.5)*6)+2025 -> 2025 | E2: 9250000 | F2: Finance and Administration
A3: Employee Training Portal | B3: Chicago Public Library | C3: Cornerstone | D3: =-INT((RAND()^1.5)*6)+2025 -> 2023 | E3: 2100000 | F3: Community Services
A4: Fleet Maintenance Dashboard | B4: Department of Business Affairs and Consumer Protection | C4: Deloitte | D4: =-INT((RAND()^1.5)*6)+2025 -> 2022 | E4: 5750000 | F4: Regulatory
A5: 311 Case Routing App | B5: Chicago Police Department | C5: IBM | D5: =-INT((RAND()^1.5)*6)+2025 -> 2025 | E5: 4900000 | F5: Public Safety
A6: Public Health Inspection Tracker | B6: Department of Cultural Affairs and Special Events | C6: CGI | D6: =-INT((RAND()^1.5)*6)+2025 -> 2025 | E6: 6000000 | F6: City Development
A7: Grants Management System | B7: Department of Cultural Affairs and Special Events | C7: Oracle | D7: =-INT((RAND()^1.5)*6)+2025 -> 2023 | E7: 8000000 | F7: City Development
A8: Payroll Adjustment Tool | B8: Office of Budget and Management | C8: SAP | D8: =-INT((RAND()^1.5)*6)+2025 -> 2025 | E8: 3750000 | F8: Finance and Administration
A9: Crime Analytics Portal | B9: Department of Streets and Sanitation | C9: Palantir | D9: =-INT((RAND()^1.5)*6)+2025 -> 2025 | E9: 9500000 | F9: Infrastructure Services
A10: Park Reservation App | B10: Chicago Police Department | C10: Infosys | D10: =-INT((RAND()^1.5)*6)+2025 -> 2025 | E10: 1500000 | F10: Public Safety
A11: Zoning Map Interface | B11: Department of Buildings | C11: ESRI | D11: =-INT((RAND()^1.5)*6)+2025 -> 2025 | E11: 4250000 | F11: Regulatory
A12: Procurement Workflow Tool | B12: Office of the Mayor | C12: KPMG | D12: =-INT((RAND()^1.5)*6)+2025 -> 2020 | E12: 3400000 | F12: Finance and Administration
A13: Vendor Risk Portal | B13: Chicago Public Library | C13: PwC | D13: =-INT((RAND()^1.5)*6)+2025 -> 2025 | E13: 2700000 | F13: Community Services
... A101: Digital Records Archive B | B101: Department of Housing | C101: OpenText | D101: =-INT((RAND()^1.5)*6)+2025 -> 2024 | E101: 8000000 | F101: City Development

Sheet Structure
A1: Component lvl 1 | B1: Component lvl 2 | C1: Component Lowest
A2: Applications | B2: Collaboration | C2: Application Components (Core)
A3: Applications | B3: External Facing | C3: Application Interface
A4: Applications | B4: Workflow | C4: Application Workflow
A5: Applications | B5: Analysis | C5: Application Logic
A6: Applications | B6: Collaboration | C6: Application Integration
A7: Applications | B7: Collaboration | C7: Application Security
A8: Infrastructure | B8: Communications | C8: Platform
A9: Infrastructure | B9: Integration | C9: Integration Services
A10: Infrastructure | B10: Communications | C10: Permission/Security
A11: Infrastructure | B11: Data | C11: Content/Data Repositories
A12: Infrastructure | B12: Communications | C12: Core Infrastructure
... A41: Infrastructure | B41: Communications | C41: Analytics Infrastructure

Sheet Criticality Score
B1: Applications | C1: Applications | D1: Applications | E1: Applications | F1: Applications | G1: Applications | H1: Infrastructure | I1: Infrastructure | J1: Infrastructure | K1: Infrastructure | L1: Infrastructure | M1: Infrastructure | N1: Infrastructure | O1: Infrastructure | P1: Infrastructure | Q1: Infrastructure | R1: Infrastructure | S1: Infrastructure | T1: Infrastructure | U1: Infrastructure | V1: Infrastructure | W1: Infrastructure | X1: Infrastructure | Y1: Infrastructure | Z1: Infrastructure | AA1: Infrastructure | AB1: Infrastructure | AC1: Infrastructure | AD1: Infrastructure | AE1: Infrastructure | AF1: Infrastructure | AG1: Infrastructure | AH1: Infrastructure | AI1: Infrastructure | AJ1: Infrastructure | AK1: Infrastructure | AL1: Infrastructure | AM1: Infrastructure | AN1: Infrastructure | AO1: Infrastructure
A2: App Name | B2: Application Components (Core) | C2: Application Interface | D2: Application Workflow | E2: Application Logic | F2: Application Integration | G2: Application Security | H2: Platform | I2: Integration Services | J2: Permission/Security | K2: Content/Data Repositories | L2: Core Infrastructure | M2: Network Services | N2: Storage Systems | O2: Compute Resources | P2: Database Services | Q2: Monitoring/Observability | R2: Backup/Recovery | S2: Load Balancing | T2: CDN/Caching | U2: API Gateway | V2: Service Mesh | W2: Container Orchestration | X2: CI/CD Pipeline | Y2: Configuration Management | Z2: Secret Management | AA2: Identity/Access Management | AB2: Logging Infrastructure | AC2: Message Queue/Event Bus | AD2: Search Services | AE2: File/Object Storage | AF2: DNS Management | AG2: SSL/Certificate Management | AH2: Firewall/WAF | AI2: DDoS Protection | AJ2: Compliance/Audit Infrastructure | AK2: Disaster Recovery | AL2: Dev/Test Environments | AM2: Performance Testing Infra | AN2: Data Pipeline/ETL | AO2: Analytics Infrastructure
A3: Building Permit Processing System | B3: =INT(5*RAND()^(VLOOKUP($A3,Sheet1!$A$3:$B$102,2,0)+VLOOKUP(B$2,Sheet1!$C$3:$D$102,2,0))/2+1) -> 2 | C3: =INT(5*RAND()^(VLOOKUP($A3,Sheet1!$A$3:$B$102,2,0)+VLOOKUP(C$2,Sheet1!$C$3:$D$102,2,0))/2+1) -> 1 | D3: =INT(5*RAND()^(VLOOKUP($A3,Sheet1!$A$3:$B$102,2,0)+VLOOKUP(D$2,Sheet1!$C$3:$D$102,2,0))/2+1) -> 2 | E3: =INT(5*RAND()^(VLOOKUP($A3,Sheet1!$A$3:$B$102,2,0)+VLOOKUP(E$2,Sheet1!$C$3:$D$102,2,0))/2+1) -> 1 | F3: =INT(5*RAND()^(VLOOKUP($A3,Sheet1!$A$3:$B$102,2,0)+VLOOKUP(F$2,Sheet1!$C$3:$D$102,2,0))/2+1) -> 1 | G3: =INT(5*RAND()^(VLOOKUP($A3,Sheet1!$A$3:$B$102,2,0)+VLOOKUP(G$2,Sheet1!$C$3:$D$102,2,0))/2+1) -> 1 | H3: =INT(5*RAND()^(VLOOKUP($A3,Sheet1!$A$3:$B$102,2,0)+VLOOKUP(H$2,Sheet1!$C$3:$D$102,2,0))/2+1) -> 2 | I3: =INT(5*RAND()^(VLOOKUP($A3,Sheet1!$A$3:$B$102,2,0)+VLOOKUP(I$2,Sheet1!$C$3:$D$102,2,0))/2+1) -> 1 | ... AO3: =INT(5*RAND()^(VLOOKUP($A3,Sheet1!$A$3:$B$102,2,0)+VLOOKUP(AO$2,Sheet1!$C$3:$D$102,2,0))/2+1) -> 1
A4: Employee Training Portal | B4: =INT(5*RAND()^(VLOOKUP($A4,Sheet1!$A$3:$B$102,2,0)+VLOOKUP(B$2,Sheet1!$C$3:$D$102,2,0))/2+1) -> 1 | C4: =INT(5*RAND()^(VLOOKUP($A4,Sheet1!$A$3:$B$102,2,0)+VLOOKUP(C$2,Sheet1!$C$3:$D$102,2,0))/2+1) -> 1 | D4: =INT(5*RAND()^(VLOOKUP($A4,Sheet1!$A$3:$B$102,2,0)+VLOOKUP(D$2,Sheet1!$C$3:$D$102,2,0))/2+1) -> 1 | E4: =INT(5*RAND()^(VLOOKUP($A4,Sheet1!$A$3:$B$102,2,0)+VLOOKUP(E$2,Sheet1!$C$3:$D$102,2,0))/2+1) -> 1 | F4: =INT(5*RAND()^(VLOOKUP($A4,Sheet1!$A$3:$B$102,2,0)+VLOOKUP(F$2,Sheet1!$C$3:$D$102,2,0))/2+1) -> 2 | G4: =INT(5*RAND()^(VLOOKUP($A4,Sheet1!$A$3:$B$102,2,0)+VLOOKUP(G$2,Sheet1!$C$3:$D$102,2,0))/2+1) -> 1 | H4: =INT(5*RAND()^(VLOOKUP($A4,Sheet1!$A$3:$B$102,2,0)+VLOOKUP(H$2,Sheet1!$C$3:$D$102,2,0))/2+1) -> 1 | I4: =INT(5*RAND()^(VLOOKUP($A4,Sheet1!$A$3:$B$102,2,0)+VLOOKUP(I$2,Sheet1!$C$3:$D$102,2,0))/2+1) -> 1 | ... AO4: =INT(5*RAND()^(VLOOKUP($A4,Sheet1!$A$3:$B$102,2,0)+VLOOKUP(AO$2,Sheet1!$C$3:$D$102,2,0))/2+1) -> 1
A5: Fleet Maintenance Dashboard | B5: =INT(5*RAND()^(VLOOKUP($A5,Sheet1!$A$3:$B$102,2,0)+VLOOKUP(B$2,Sheet1!$C$3:$D$102,2,0))/2+1) -> 2 | C5: =INT(5*RAND()^(VLOOKUP($A5,Sheet1!$A$3:$B$102,2,0)+VLOOKUP(C$2,Sheet1!$C$3:$D$102,2,0))/2+1) -> 1 | D5: =INT(5*RAND()^(VLOOKUP($A5,Sheet1!$A$3:$B$102,2,0)+VLOOKUP(D$2,Sheet1!$C$3:$D$102,2,0))/2+1) -> 1 | E5: =INT(5*RAND()^(VLOOKUP($A5,Sheet1!$A$3:$B$102,2,0)+VLOOKUP(E$2,Sheet1!$C$3:$D$102,2,0))/2+1) -> 1 | F5: =INT(5*RAND()^(VLOOKUP($A5,Sheet1!$A$3:$B$102,2,0)+VLOOKUP(F$2,Sheet1!$C$3:$D$102,2,0))/2+1) -> 1 | G5: =INT(5*RAND()^(VLOOKUP($A5,Sheet1!$A$3:$B$102,2,0)+VLOOKUP(G$2,Sheet1!$C$3:$D$102,2,0))/2+1) -> 1 | H5: =INT(5*RAND()^(VLOOKUP($A5,Sheet1!$A$3:$B$102,2,0)+VLOOKUP(H$2,Sheet1!$C$3:$D$102,2,0))/2+1) -> 1 | I5: =INT(5*RAND()^(VLOOKUP($A5,Sheet1!$A$3:$B$102,2,0)+VLOOKUP(I$2,Sheet1!$C$3:$D$102,2,0))/2+1) -> 2 | ... AO5: =INT(5*RAND()^(VLOOKUP($A5,Sheet1!$A$3:$B$102,2,0)+VLOOKUP(AO$2,Sheet1!$C$3:$D$102,2,0))/2+1) -> 1
A6: 311 Case Routing App | B6: =INT(5*RAND()^(VLOOKUP($A6,Sheet1!$A$3:$B$102,2,0)+VLOOKUP(B$2,Sheet1!$C$3:$D$102,2,0))/2+1) -> 1 | C6: =INT(5*RAND()^(VLOOKUP($A6,Sheet1!$A$3:$B$102,2,0)+VLOOKUP(C$2,Sheet1!$C$3:$D$102,2,0))/2+1) -> 1 | D6: =INT(5*RAND()^(VLOOKUP($A6,Sheet1!$A$3:$B$102,2,0)+VLOOKUP(D$2,Sheet1!$C$3:$D$102,2,0))/2+1) -> 2 | E6: =INT(5*RAND()^(VLOOKUP($A6,Sheet1!$A$3:$B$102,2,0)+VLOOKUP(E$2,Sheet1!$C$3:$D$102,2,0))/2+1) -> 1 | F6: =INT(5*RAND()^(VLOOKUP($A6,Sheet1!$A$3:$B$102,2,0)+VLOOKUP(F$2,Sheet1!$C$3:$D$102,2,0))/2+1) -> 2 | G6: =INT(5*RAND()^(VLOOKUP($A6,Sheet1!$A$3:$B$102,2,0)+VLOOKUP(G$2,Sheet1!$C$3:$D$102,2,0))/2+1) -> 1 | H6: =INT(5*RAND()^(VLOOKUP($A6,Sheet1!$A$3:$B$102,2,0)+VLOOKUP(H$2,Sheet1!$C$3:$D$102,2,0))/2+1) -> 2 | I6: =INT(5*RAND()^(VLOOKUP($A6,Sheet1!$A$3:$B$102,2,0)+VLOOKUP(I$2,Sheet1!$C$3:$D$102,2,0))/2+1) -> 1 | ... AO6: =INT(5*RAND()^(VLOOKUP($A6,Sheet1!$A$3:$B$102,2,0)+VLOOKUP(AO$2,Sheet1!$C$3:$D$102,2,0))/2+1) -> 2
A7: Public Health Inspection Tracker | B7: =INT(5*RAND()^(VLOOKUP($A7,Sheet1!$A$3:$B$102,2,0)+VLOOKUP(B$2,Sheet1!$C$3:$D$102,2,0))/2+1) -> 1 | C7: =INT(5*RAND()^(VLOOKUP($A7,Sheet1!$A$3:$B$102,2,0)+VLOOKUP(C$2,Sheet1!$C$3:$D$102,2,0))/2+1) -> 1 | D7: =INT(5*RAND()^(VLOOKUP($A7,Sheet1!$A$3:$B$102,2,0)+VLOOKUP(D$2,Sheet1!$C$3:$D$102,2,0))/2+1) -> 1 | E7: =INT(5*RAND()^(VLOOKUP($A7,Sheet1!$A$3:$B$102,2,0)+VLOOKUP(E$2,Sheet1!$C$3:$D$102,2,0))/2+1) -> 2 | F7: =INT(5*RAND()^(VLOOKUP($A7,Sheet1!$A$3:$B$102,2,0)+VLOOKUP(F$2,Sheet1!$C$3:$D$102,2,0))/2+1) -> 1 | G7: =INT(5*RAND()^(VLOOKUP($A7,Sheet1!$A$3:$B$102,2,0)+VLOOKUP(G$2,Sheet1!$C$3:$D$102,2,0))/2+1) -> 1 | H7: =INT(5*RAND()^(VLOOKUP($A7,Sheet1!$A$3:$B$102,2,0)+VLOOKUP(H$2,Sheet1!$C$3:$D$102,2,0))/2+1) -> 1 | I7: =INT(5*RAND()^(VLOOKUP($A7,Sheet1!$A$3:$B$102,2,0)+VLOOKUP(I$2,Sheet1!$C$3:$D$102,2,0))/2+1) -> 1 | ... AO7: =INT(5*RAND()^(VLOOKUP($A7,Sheet1!$A$3:$B$102,2,0)+VLOOKUP(AO$2,Sheet1!$C$3:$D$102,2,0))/2+1) -> 1
A8: Grants Management System | B8: =INT(5*RAND()^(VLOOKUP($A8,Sheet1!$A$3:$B$102,2,0)+VLOOKUP(B$2,Sheet1!$C$3:$D$102,2,0))/2+1) -> 1 | C8: =INT(5*RAND()^(VLOOKUP($A8,Sheet1!$A$3:$B$102,2,0)+VLOOKUP(C$2,Sheet1!$C$3:$D$102,2,0))/2+1) -> 1 | D8: =INT(5*RAND()^(VLOOKUP($A8,Sheet1!$A$3:$B$102,2,0)+VLOOKUP(D$2,Sheet1!$C$3:$D$102,2,0))/2+1) -> 1 | E8: =INT(5*RAND()^(VLOOKUP($A8,Sheet1!$A$3:$B$102,2,0)+VLOOKUP(E$2,Sheet1!$C$3:$D$102,2,0))/2+1) -> 1 | F8: =INT(5*RAND()^(VLOOKUP($A8,Sheet1!$A$3:$B$102,2,0)+VLOOKUP(F$2,Sheet1!$C$3:$D$102,2,0))/2+1) -> 1 | G8: =INT(5*RAND()^(VLOOKUP($A8,Sheet1!$A$3:$B$102,2,0)+VLOOKUP(G$2,Sheet1!$C$3:$D$102,2,0))/2+1) -> 1 | H8: =INT(5*RAND()^(VLOOKUP($A8,Sheet1!$A$3:$B$102,2,0)+VLOOKUP(H$2,Sheet1!$C$3:$D$102,2,0))/2+1) -> 2 | I8: =INT(5*RAND()^(VLOOKUP($A8,Sheet1!$A$3:$B$102,2,0)+VLOOKUP(I$2,Sheet1!$C$3:$D$102,2,0))/2+1) -> 1 | ... AO8: =INT(5*RAND()^(VLOOKUP($A8,Sheet1!$A$3:$B$102,2,0)+VLOOKUP(AO$2,Sheet1!$C$3:$D$102,2,0))/2+1) -> 1
A9: Payroll Adjustment Tool | B9: =INT(5*RAND()^(VLOOKUP($A9,Sheet1!$A$3:$B$102,2,0)+VLOOKUP(B$2,Sheet1!$C$3:$D$102,2,0))/2+1) -> 1 | C9: =INT(5*RAND()^(VLOOKUP($A9,Sheet1!$A$3:$B$102,2,0)+VLOOKUP(C$2,Sheet1!$C$3:$D$102,2,0))/2+1) -> 1 | D9: =INT(5*RAND()^(VLOOKUP($A9,Sheet1!$A$3:$B$102,2,0)+VLOOKUP(D$2,Sheet1!$C$3:$D$102,2,0))/2+1) -> 1 | E9: =INT(5*RAND()^(VLOOKUP($A9,Sheet1!$A$3:$B$102,2,0)+VLOOKUP(E$2,Sheet1!$C$3:$D$102,2,0))/2+1) -> 1 | F9: =INT(5*RAND()^(VLOOKUP($A9,Sheet1!$A$3:$B$102,2,0)+VLOOKUP(F$2,Sheet1!$C$3:$D$102,2,0))/2+1) -> 1 | G9: =INT(5*RAND()^(VLOOKUP($A9,Sheet1!$A$3:$B$102,2,0)+VLOOKUP(G$2,Sheet1!$C$3:$D$102,2,0))/2+1) -> 1 | H9: =INT(5*RAND()^(VLOOKUP($A9,Sheet1!$A$3:$B$102,2,0)+VLOOKUP(H$2,Sheet1!$C$3:$D$102,2,0))/2+1) -> 1 | I9: =INT(5*RAND()^(VLOOKUP($A9,Sheet1!$A$3:$B$102,2,0)+VLOOKUP(I$2,Sheet1!$C$3:$D$102,2,0))/2+1) -> 1 | ... AO9: =INT(5*RAND()^(VLOOKUP($A9,Sheet1!$A$3:$B$102,2,0)+VLOOKUP(AO$2,Sheet1!$C$3:$D$102,2,0))/2+1) -> 1
A10: Crime Analytics Portal | B10: =INT(5*RAND()^(VLOOKUP($A10,Sheet1!$A$3:$B$102,2,0)+VLOOKUP(B$2,Sheet1!$C$3:$D$102,2,0))/2+1) -> 1 | C10: =INT(5*RAND()^(VLOOKUP($A10,Sheet1!$A$3:$B$102,2,0)+VLOOKUP(C$2,Sheet1!$C$3:$D$102,2,0))/2+1) -> 1 | D10: =INT(5*RAND()^(VLOOKUP($A10,Sheet1!$A$3:$B$102,2,0)+VLOOKUP(D$2,Sheet1!$C$3:$D$102,2,0))/2+1) -> 1 | E10: =INT(5*RAND()^(VLOOKUP($A10,Sheet1!$A$3:$B$102,2,0)+VLOOKUP(E$2,Sheet1!$C$3:$D$102,2,0))/2+1) -> 1 | F10: =INT(5*RAND()^(VLOOKUP($A10,Sheet1!$A$3:$B$102,2,0)+VLOOKUP(F$2,Sheet1!$C$3:$D$102,2,0))/2+1) -> 3 | G10: =INT(5*RAND()^(VLOOKUP($A10,Sheet1!$A$3:$B$102,2,0)+VLOOKUP(G$2,Sheet1!$C$3:$D$102,2,0))/2+1) -> 1 | H10: =INT(5*RAND()^(VLOOKUP($A10,Sheet1!$A$3:$B$102,2,0)+VLOOKUP(H$2,Sheet1!$C$3:$D$102,2,0))/2+1) -> 1 | I10: =INT(5*RAND()^(VLOOKUP($A10,Sheet1!$A$3:$B$102,2,0)+VLOOKUP(I$2,Sheet1!$C$3:$D$102,2,0))/2+1) -> 2 | ... AO10: =INT(5*RAND()^(VLOOKUP($A10,Sheet1!$A$3:$B$102,2,0)+VLOOKUP(AO$2,Sheet1!$C$3:$D$102,2,0))/2+1) -> 1
A11: Park Reservation App | B11: =INT(5*RAND()^(VLOOKUP($A11,Sheet1!$A$3:$B$102,2,0)+VLOOKUP(B$2,Sheet1!$C$3:$D$102,2,0))/2+1) -> 1 | C11: =INT(5*RAND()^(VLOOKUP($A11,Sheet1!$A$3:$B$102,2,0)+VLOOKUP(C$2,Sheet1!$C$3:$D$102,2,0))/2+1) -> 1 | D11: =INT(5*RAND()^(VLOOKUP($A11,Sheet1!$A$3:$B$102,2,0)+VLOOKUP(D$2,Sheet1!$C$3:$D$102,2,0))/2+1) -> 1 | E11: =INT(5*RAND()^(VLOOKUP($A11,Sheet1!$A$3:$B$102,2,0)+VLOOKUP(E$2,Sheet1!$C$3:$D$102,2,0))/2+1) -> 3 | F11: =INT(5*RAND()^(VLOOKUP($A11,Sheet1!$A$3:$B$102,2,0)+VLOOKUP(F$2,Sheet1!$C$3:$D$102,2,0))/2+1) -> 2 | G11: =INT(5*RAND()^(VLOOKUP($A11,Sheet1!$A$3:$B$102,2,0)+VLOOKUP(G$2,Sheet1!$C$3:$D$102,2,0))/2+1) -> 1 | H11: =INT(5*RAND()^(VLOOKUP($A11,Sheet1!$A$3:$B$102,2,0)+VLOOKUP(H$2,Sheet1!$C$3:$D$102,2,0))/2+1) -> 3 | I11: =INT(5*RAND()^(VLOOKUP($A11,Sheet1!$A$3:$B$102,2,0)+VLOOKUP(I$2,Sheet1!$C$3:$D$102,2,0))/2+1) -> 3 | ... AO11: =INT(5*RAND()^(VLOOKUP($A11,Sheet1!$A$3:$B$102,2,0)+VLOOKUP(AO$2,Sheet1!$C$3:$D$102,2,0))/2+1) -> 2
A12: Zoning Map Interface | B12: =INT(5*RAND()^(VLOOKUP($A12,Sheet1!$A$3:$B$102,2,0)+VLOOKUP(B$2,Sheet1!$C$3:$D$102,2,0))/2+1) -> 2 | C12: =INT(5*RAND()^(VLOOKUP($A12,Sheet1!$A$3:$B$102,2,0)+VLOOKUP(C$2,Sheet1!$C$3:$D$102,2,0))/2+1) -> 1 | D12: =INT(5*RAND()^(VLOOKUP($A12,Sheet1!$A$3:$B$102,2,0)+VLOOKUP(D$2,Sheet1!$C$3:$D$102,2,0))/2+1) -> 1 | E12: =INT(5*RAND()^(VLOOKUP($A12,Sheet1!$A$3:$B$102,2,0)+VLOOKUP(E$2,Sheet1!$C$3:$D$102,2,0))/2+1) -> 1 | F12: =INT(5*RAND()^(VLOOKUP($A12,Sheet1!$A$3:$B$102,2,0)+VLOOKUP(F$2,Sheet1!$C$3:$D$102,2,0))/2+1) -> 3 | G12: =INT(5*RAND()^(VLOOKUP($A12,Sheet1!$A$3:$B$102,2,0)+VLOOKUP(G$2,Sheet1!$C$3:$D$102,2,0))/2+1) -> 2 | H12: =INT(5*RAND()^(VLOOKUP($A12,Sheet1!$A$3:$B$102,2,0)+VLOOKUP(H$2,Sheet1!$C$3:$D$102,2,0))/2+1) -> 1 | I12: =INT(5*RAND()^(VLOOKUP($A12,Sheet1!$A$3:$B$102,2,0)+VLOOKUP(I$2,Sheet1!$C$3:$D$102,2,0))/2+1) -> 1 | ... AO12: =INT(5*RAND()^(VLOOKUP($A12,Sheet1!$A$3:$B$102,2,0)+VLOOKUP(AO$2,Sheet1!$C$3:$D$102,2,0))/2+1) -> 1
A13: Procurement Workflow Tool | B13: =INT(5*RAND()^(VLOOKUP($A13,Sheet1!$A$3:$B$102,2,0)+VLOOKUP(B$2,Sheet1!$C$3:$D$102,2,0))/2+1) -> 1 | C13: =INT(5*RAND()^(VLOOKUP($A13,Sheet1!$A$3:$B$102,2,0)+VLOOKUP(C$2,Sheet1!$C$3:$D$102,2,0))/2+1) -> 1 | D13: =INT(5*RAND()^(VLOOKUP($A13,Sheet1!$A$3:$B$102,2,0)+VLOOKUP(D$2,Sheet1!$C$3:$D$102,2,0))/2+1) -> 3 | E13: =INT(5*RAND()^(VLOOKUP($A13,Sheet1!$A$3:$B$102,2,0)+VLOOKUP(E$2,Sheet1!$C$3:$D$102,2,0))/2+1) -> 2 | F13: =INT(5*RAND()^(VLOOKUP($A13,Sheet1!$A$3:$B$102,2,0)+VLOOKUP(F$2,Sheet1!$C$3:$D$102,2,0))/2+1) -> 2 | G13: =INT(5*RAND()^(VLOOKUP($A13,Sheet1!$A$3:$B$102,2,0)+VLOOKUP(G$2,Sheet1!$C$3:$D$102,2,0))/2+1) -> 1 | H13: =INT(5*RAND()^(VLOOKUP($A13,Sheet1!$A$3:$B$102,2,0)+VLOOKUP(H$2,Sheet1!$C$3:$D$102,2,0))/2+1) -> 1 | I13: =INT(5*RAND()^(VLOOKUP($A13,Sheet1!$A$3:$B$102,2,0)+VLOOKUP(I$2,Sheet1!$C$3:$D$102,2,0))/2+1) -> 1 | ... AO13: =INT(5*RAND()^(VLOOKUP($A13,Sheet1!$A$3:$B$102,2,0)+VLOOKUP(AO$2,Sheet1!$C$3:$D$102,2,0))/2+1) -> 1
A14: Vendor Risk Portal | B14: =INT(5*RAND()^(VLOOKUP($A14,Sheet1!$A$3:$B$102,2,0)+VLOOKUP(B$2,Sheet1!$C$3:$D$102,2,0))/2+1) -> 1 | C14: =INT(5*RAND()^(VLOOKUP($A14,Sheet1!$A$3:$B$102,2,0)+VLOOKUP(C$2,Sheet1!$C$3:$D$102,2,0))/2+1) -> 1 | D14: =INT(5*RAND()^(VLOOKUP($A14,Sheet1!$A$3:$B$102,2,0)+VLOOKUP(D$2,Sheet1!$C$3:$D$102,2,0))/2+1) -> 1 | E14: =INT(5*RAND()^(VLOOKUP($A14,Sheet1!$A$3:$B$102,2,0)+VLOOKUP(E$2,Sheet1!$C$3:$D$102,2,0))/2+1) -> 1 | F14: =INT(5*RAND()^(VLOOKUP($A14,Sheet1!$A$3:$B$102,2,0)+VLOOKUP(F$2,Sheet1!$C$3:$D$102,2,0))/2+1) -> 3 | G14: =INT(5*RAND()^(VLOOKUP($A14,Sheet1!$A$3:$B$102,2,0)+VLOOKUP(G$2,Sheet1!$C$3:$D$102,2,0))/2+1) -> 1 | H14: =INT(5*RAND()^(VLOOKUP($A14,Sheet1!$A$3:$B$102,2,0)+VLOOKUP(H$2,Sheet1!$C$3:$D$102,2,0))/2+1) -> 1 | I14: =INT(5*RAND()^(VLOOKUP($A14,Sheet1!$A$3:$B$102,2,0)+VLOOKUP(I$2,Sheet1!$C$3:$D$102,2,0))/2+1) -> 1 | ... AO14: =INT(5*RAND()^(VLOOKUP($A14,Sheet1!$A$3:$B$102,2,0)+VLOOKUP(AO$2,Sheet1!$C$3:$D$102,2,0))/2+1) -> 1
... A102: Digital Records Archive B | B102: =INT(5*RAND()^(VLOOKUP($A102,Sheet1!$A$3:$B$102,2,0)+VLOOKUP(B$2,Sheet1!$C$3:$D$102,2,0))/2+1) -> 1 | C102: =INT(5*RAND()^(VLOOKUP($A102,Sheet1!$A$3:$B$102,2,0)+VLOOKUP(C$2,Sheet1!$C$3:$D$102,2,0))/2+1) -> 1 | D102: =INT(5*RAND()^(VLOOKUP($A102,Sheet1!$A$3:$B$102,2,0)+VLOOKUP(D$2,Sheet1!$C$3:$D$102,2,0))/2+1) -> 1 | E102: =INT(5*RAND()^(VLOOKUP($A102,Sheet1!$A$3:$B$102,2,0)+VLOOKUP(E$2,Sheet1!$C$3:$D$102,2,0))/2+1) -> 1 | F102: =INT(5*RAND()^(VLOOKUP($A102,Sheet1!$A$3:$B$102,2,0)+VLOOKUP(F$2,Sheet1!$C$3:$D$102,2,0))/2+1) -> 1 | G102: =INT(5*RAND()^(VLOOKUP($A102,Sheet1!$A$3:$B$102,2,0)+VLOOKUP(G$2,Sheet1!$C$3:$D$102,2,0))/2+1) -> 2 | H102: =INT(5*RAND()^(VLOOKUP($A102,Sheet1!$A$3:$B$102,2,0)+VLOOKUP(H$2,Sheet1!$C$3:$D$102,2,0))/2+1) -> 1 | I102: =INT(5*RAND()^(VLOOKUP($A102,Sheet1!$A$3:$B$102,2,0)+VLOOKUP(I$2,Sheet1!$C$3:$D$102,2,0))/2+1) -> 1 | ... AO102: =INT(5*RAND()^(VLOOKUP($A102,Sheet1!$A$3:$B$102,2,0)+VLOOKUP(AO$2,Sheet1!$C$3:$D$102,2,0))/2+1) -> 3

Sheet Sheet1
A2: App Name
A3: Building Permit Processing System | B3: =INT(RAND()*3+1) -> 3 | C3: Application Components (Core) | D3: =INT(RAND()*3+1) -> 1
A4: Employee Training Portal | B4: =INT(RAND()*3+1) -> 2 | C4: Application Interface | D4: =INT(RAND()*3+1) -> 3
A5: Fleet Maintenance Dashboard | B5: =INT(RAND()*3+1) -> 1 | C5: Application Workflow | D5: =INT(RAND()*3+1) -> 1
A6: 311 Case Routing App | B6: =INT(RAND()*3+1) -> 1 | C6: Application Logic | D6: =INT(RAND()*3+1) -> 1
A7: Public Health Inspection Tracker | B7: =INT(RAND()*3+1) -> 3 | C7: Application Integration | D7: =INT(RAND()*3+1) -> 1
A8: Grants Management System | B8: =INT(RAND()*3+1) -> 3 | C8: Application Security | D8: =INT(RAND()*3+1) -> 2
A9: Payroll Adjustment Tool | B9: =INT(RAND()*3+1) -> 2 | C9: Platform | D9: =INT(RAND()*3+1) -> 3
A10: Crime Analytics Portal | B10: =INT(RAND()*3+1) -> 1 | C10: Integration Services | D10: =INT(RAND()*3+1) -> 1
A11: Park Reservation App | B11: =INT(RAND()*3+1) -> 1 | C11: Permission/Security | D11: =INT(RAND()*3+1) -> 2
A12: Zoning Map Interface | B12: =INT(RAND()*3+1) -> 2 | C12: Content/Data Repositories | D12: =INT(RAND()*3+1) -> 2
A13: Procurement Workflow Tool | B13: =INT(RAND()*3+1) -> 3 | C13: Core Infrastructure | D13: =INT(RAND()*3+1) -> 2
A14: Vendor Risk Portal | B14: =INT(RAND()*3+1) -> 2 | C14: Network Services | D14: =INT(RAND()*3+1) -> 3
... A42: Grant Performance Dashboard | B42: =INT(RAND()*3+1) -> 2 | C42: Analytics Infrastructure | D42: =INT(RAND()*3+1) -> 2
A43: Urban Planning Simulator | B43: =INT(RAND()*3+1) -> 2 | D43: =INT(RAND()*3+1) -> 2
A44: HR Recruitment Tracker | B44: =INT(RAND()*3+1) -> 3 | D44: =INT(RAND()*3+1) -> 1
A45: Cyber Incident Response Tool | B45: =INT(RAND()*3+1) -> 1 | D45: =INT(RAND()*3+1) -> 3
A46: Court Fine Collection Portal | B46: =INT(RAND()*3+1) -> 2 | D46: =INT(RAND()*3+1) -> 1
A47: Property Records Viewer | B47: =INT(RAND()*3+1) -> 1 | D47: =INT(RAND()*3+1) -> 3
A48: Volunteer Management App | B48: =INT(RAND()*3+1) -> 1 | D48: =INT(RAND()*3+1) -> 1
A49: Budget Transparency Portal | B49: =INT(RAND()*3+1) -> 3 | D49: =INT(RAND()*3+1) -> 3
A50: Emergency Shelter Tracker | B50: =INT(RAND()*3+1) -> 1 | D50: =INT(RAND()*3+1) -> 1
A51: Environmental Permit App | B51: =INT(RAND()*3+1) -> 1 | D51: =INT(RAND()*3+1) -> 1
A52: Digital Records Archive | B52: =INT(RAND()*3+1) -> 2 | D52: =INT(RAND()*3+1) -> 1
A53: Building Permit Processing System B | B53: =INT(RAND()*3+1) -> 3 | D53: =INT(RAND()*3+1) -> 2
A54: Employee Training Portal B | B54: =INT(RAND()*3+1) -> 1 | D54: =INT(RAND()*3+1) -> 1
... A102: Digital Records Archive B | B102: =INT(RAND()*3+1) -> 2 | D102: =INT(RAND()*3+1) -> 3

Sheet Specificity Score
B1: Applications | C1: Applications | D1: Applications | E1: Applications | F1: Applications | G1: Applications | H1: Infrastructure | I1: Infrastructure | J1: Infrastructure | K1: Infrastructure | L1: Infrastructure | M1: Infrastructure | N1: Infrastructure | O1: Infrastructure | P1: Infrastructure | Q1: Infrastructure | R1: Infrastructure | S1: Infrastructure | T1: Infrastructure | U1: Infrastructure | V1: Infrastructure | W1: Infrastructure | X1: Infrastructure | Y1: Infrastructure | Z1: Infrastructure | AA1: Infrastructure | AB1: Infrastructure | AC1: Infrastructure | AD1: Infrastructure | AE1: Infrastructure | AF1: Infrastructure | AG1: Infrastructure | AH1: Infrastructure | AI1: Infrastructure | AJ1: Infrastructure | AK1: Infrastructure | AL1: Infrastructure | AM1: Infrastructure | AN1: Infrastructure | AO1: Infrastructure
A2: App Name | B2: Application Components (Core) | C2: Application Interface | D2: Application Workflow | E2: Application Logic | F2: Application Integration | G2: Application Security | H2: Platform | I2: Integration Services | J2: Permission/Security | K2: Content/Data Repositories | L2: Core Infrastructure | M2: Network Services | N2: Storage Systems | O2: Compute Resources | P2: Database Services | Q2: Monitoring/Observability | R2: Backup/Recovery | S2: Load Balancing | T2: CDN/Caching | U2: API Gateway | V2: Service Mesh | W2: Container Orchestration | X2: CI/CD Pipeline | Y2: Configuration Management | Z2: Secret Management | AA2: Identity/Access Management | AB2: Logging Infrastructure | AC2: Message Queue/Event Bus | AD2: Search Services | AE2: File/Object Storage | AF2: DNS Management | AG2: SSL/Certificate Management | AH2: Firewall/WAF | AI2: DDoS Protection | AJ2: Compliance/Audit Infrastructure | AK2: Disaster Recovery | AL2: Dev/Test Environments | AM2: Performance Testing Infra | AN2: Data Pipeline/ETL | AO2: Analytics Infrastructure
A3: Building Permit Processing System | B3: =INT(5*RAND()^3)+1 -> 1 | C3: =INT(5*RAND()^3)+1 -> 1 | D3: =INT(5*RAND()^3)+1 -> 1 | E3: =INT(5*RAND()^3)+1 -> 1 | F3: =INT(5*RAND()^3)+1 -> 1 | G3: =INT(5*RAND()^3)+1 -> 3 | H3: =INT(5*RAND()^3)+1 -> 4 | I3: =INT(5*RAND()^3)+1 -> 2 | ... AO3: =INT(5*RAND()^3)+1 -> 2
A4: Employee Training Portal | B4: =INT(5*RAND()^3)+1 -> 1 | C4: =INT(5*RAND()^3)+1 -> 1 | D4: =INT(5*RAND()^3)+1 -> 1 | E4: =INT(5*RAND()^3)+1 -> 2 | F4: =INT(5*RAND()^3)+1 -> 1 | G4: =INT(5*RAND()^3)+1 -> 4 | H4: =INT(5*RAND()^3)+1 -> 4 | I4: =INT(5*RAND()^3)+1 -> 3 | ... AO4: =INT(5*RAND()^3)+1 -> 1
A5: Fleet Maintenance Dashboard | B5: =INT(5*RAND()^3)+1 -> 2 | C5: =INT(5*RAND()^3)+1 -> 2 | D5: =INT(5*RAND()^3)+1 -> 1 | E5: =INT(5*RAND()^3)+1 -> 4 | F5: =INT(5*RAND()^3)+1 -> 1 | G5: =INT(5*RAND()^3)+1 -> 3 | H5: =INT(5*RAND()^3)+1 -> 1 | I5: =INT(5*RAND()^3)+1 -> 3 | ... AO5: =INT(5*RAND()^3)+1 -> 3
A6: 311 Case Routing App | B6: =INT(5*RAND()^3)+1 -> 1 | C6: =INT(5*RAND()^3)+1 -> 1 | D6: =INT(5*RAND()^3)+1 -> 1 | E6: =INT(5*RAND()^3)+1 -> 4 | F6: =INT(5*RAND()^3)+1 -> 1 | G6: =INT(5*RAND()^3)+1 -> 3 | H6: =INT(5*RAND()^3)+1 -> 1 | I6: =INT(5*RAND()^3)+1 -> 1 | ... AO6: =INT(5*RAND()^3)+1 -> 5
A7: Public Health Inspection Tracker | B7: =INT(5*RAND()^3)+1 -> 1 | C7: =INT(5*RAND()^3)+1 -> 1 | D7: =INT(5*RAND()^3)+1 -> 1 | E7: =INT(5*RAND()^3)+1 -> 4 | F7: =INT(5*RAND()^3)+1 -> 5 | G7: =INT(5*RAND()^3)+1 -> 1 | H7: =INT(5*RAND()^3)+1 -> 1 | I7: =INT(5*RAND()^3)+1 -> 1 | ... AO7: =INT(5*RAND()^3)+1 -> 1
A8: Grants Management System | B8: =INT(5*RAND()^3)+1 -> 5 | C8: =INT(5*RAND()^3)+1 -> 1 | D8: =INT(5*RAND()^3)+1 -> 1 | E8: =INT(5*RAND()^3)+1 -> 1 | F8: =INT(5*RAND()^3)+1 -> 1 | G8: =INT(5*RAND()^3)+1 -> 1 | H8: =INT(5*RAND()^3)+1 -> 2 | I8: =INT(5*RAND()^3)+1 -> 1 | ... AO8: =INT(5*RAND()^3)+1 -> 1
A9: Payroll Adjustment Tool | B9: =INT(5*RAND()^3)+1 -> 5 | C9: =INT(5*RAND()^3)+1 -> 5 | D9: =INT(5*RAND()^3)+1 -> 1 | E9: =INT(5*RAND()^3)+1 -> 1 | F9: =INT(5*RAND()^3)+1 -> 2 | G9: =INT(5*RAND()^3)+1 -> 1 | H9: =INT(5*RAND()^3)+1 -> 5 | I9: =INT(5*RAND()^3)+1 -> 1 | ... AO9: =INT(5*RAND()^3)+1 -> 1
A10: Crime Analytics Portal | B10: =INT(5*RAND()^3)+1 -> 1 | C10: =INT(5*RAND()^3)+1 -> 5 | D10: =INT(5*RAND()^3)+1 -> 2 | E10: =INT(5*RAND()^3)+1 -> 2 | F10: =INT(5*RAND()^3)+1 -> 2 | G10: =INT(5*RAND()^3)+1 -> 5 | H10: =INT(5*RAND()^3)+1 -> 2 | I10: =INT(5*RAND()^3)+1 -> 3 | ... AO10: =INT(5*RAND()^3)+1 -> 3
A11: Park Reservation App | B11: =INT(5*RAND()^3)+1 -> 5 | C11: =INT(5*RAND()^3)+1 -> 1 | D11: =INT(5*RAND()^3)+1 -> 1 | E11: =INT(5*RAND()^3)+1 -> 1 | F11: =INT(5*RAND()^3)+1 -> 1 | G11: =INT(5*RAND()^3)+1 -> 3 | H11: =INT(5*RAND()^3)+1 -> 2 | I11: =INT(5*RAND()^3)+1 -> 4 | ... AO11: =INT(5*RAND()^3)+1 -> 2
A12: Zoning Map Interface | B12: =INT(5*RAND()^3)+1 -> 1 | C12: =INT(5*RAND()^3)+1 -> 1 | D12: =INT(5*RAND()^3)+1 -> 1 | E12: =INT(5*RAND()^3)+1 -> 1 | F12: =INT(5*RAND()^3)+1 -> 1 | G12: =INT(5*RAND()^3)+1 -> 1 | H12: =INT(5*RAND()^3)+1 -> 1 | I12: =INT(5*RAND()^3)+1 -> 1 | ... AO12: =INT(5*RAND()^3)+1 -> 1
A13: Procurement Workflow Tool | B13: =INT(5*RAND()^3)+1 -> 1 | C13: =INT(5*RAND()^3)+1 -> 5 | D13: =INT(5*RAND()^3)+1 -> 2 | E13: =INT(5*RAND()^3)+1 -> 1 | F13: =INT(5*RAND()^3)+1 -> 3 | G13: =INT(5*RAND()^3)+1 -> 4 | H13: =INT(5*RAND()^3)+1 -> 1 | I13: =INT(5*RAND()^3)+1 -> 5 | ... AO13: =INT(5*RAND()^3)+1 -> 1
A14: Vendor Risk Portal | B14: =INT(5*RAND()^3)+1 -> 3 | C14: =INT(5*RAND()^3)+1 -> 1 | D14: =INT(5*RAND()^3)+1 -> 1 | E14: =INT(5*RAND()^3)+1 -> 1 | F14: =INT(5*RAND()^3)+1 -> 1 | G14: =INT(5*RAND()^3)+1 -> 1 | H14: =INT(5*RAND()^3)+1 -> 1 | I14: =INT(5*RAND()^3)+1 -> 2 | ... AO14: =INT(5*RAND()^3)+1 -> 4
... A102: Digital Records Archive B | B102: =INT(5*RAND()^3)+1 -> 1 | C102: =INT(5*RAND()^3)+1 -> 1 | D102: =INT(5*RAND()^3)+1 -> 1 | E102: =INT(5*RAND()^3)+1 -> 4 | F102: =INT(5*RAND()^3)+1 -> 3 | G102: =INT(5*RAND()^3)+1 -> 3 | H102: =INT(5*RAND()^3)+1 -> 1 | I102: =INT(5*RAND()^3)+1 -> 1 | ... AO102: =INT(5*RAND()^3)+1 -> 2

Sheet IA Engagement Time
A1: App Name | B1: Requirements Gathering & Analysis | C1: Solution Design & Architecture | D1: Stakeholder Alignment & Change Mgmt | E1: Configuration & Customization | F1: Integration Development | G1: Testing & Quality Assurance | H1: Documentation & Knowledge Transfer | I1: Project Management & Governance | J1: Training & Enablement | K1: Ongoing Support & Optimization
A2: Building Permit Processing System | B2: =RAND()*0.15+0.05 -> 0.086281448 | C2: =RAND()*0.15+0.05 -> 0.14964183 | D2: =RAND()*0.15+0.05 -> 0.13903553 | E2: =RAND()*0.15+0.05 -> 0.089763138 | F2: =RAND()*0.15+0.05 -> 0.11294381 | G2: =RAND()*0.15+0.05 -> 0.13038309 | H2: =RAND()*0.15+0.05 -> 0.053464814 | I2: =RAND()*0.15+0.05 -> 0.11487291 | ... K2: =RAND()*0.15+0.05 -> 0.18016269
A3: Employee Training Portal | B3: =RAND()*0.15+0.05 -> 0.05913268 | C3: =RAND()*0.15+0.05 -> 0.13272071 | D3: =RAND()*0.15+0.05 -> 0.15806212 | E3: =RAND()*0.15+0.05 -> 0.16068149 | F3: =RAND()*0.15+0.05 -> 0.066117972 | G3: =RAND()*0.15+0.05 -> 0.14710305 | H3: =RAND()*0.15+0.05 -> 0.10178931 | I3: =RAND()*0.15+0.05 -> 0.1112181 | ... K3: =RAND()*0.15+0.05 -> 0.15267008
A4: Fleet Maintenance Dashboard | B4: =RAND()*0.15+0.05 -> 0.18898581 | C4: =RAND()*0.15+0.05 -> 0.16629102 | D4: =RAND()*0.15+0.05 -> 0.068158747 | E4: =RAND()*0.15+0.05 -> 0.081691165 | F4: =RAND()*0.15+0.05 -> 0.089014359 | G4: =RAND()*0.15+0.05 -> 0.17011716 | H4: =RAND()*0.15+0.05 -> 0.086482171 | I4: =RAND()*0.15+0.05 -> 0.096148888 | ... K4: =RAND()*0.15+0.05 -> 0.17014996
A5: 311 Case Routing App | B5: =RAND()*0.15+0.05 -> 0.096169345 | C5: =RAND()*0.15+0.05 -> 0.11813672 | D5: =RAND()*0.15+0.05 -> 0.062386697 | E5: =RAND()*0.15+0.05 -> 0.15000248 | F5: =RAND()*0.15+0.05 -> 0.084139157 | G5: =RAND()*0.15+0.05 -> 0.13182625 | H5: =RAND()*0.15+0.05 -> 0.052402069 | I5: =RAND()*0.15+0.05 -> 0.062781339 | ... K5: =RAND()*0.15+0.05 -> 0.18412523
A6: Public Health Inspection Tracker | B6: =RAND()*0.15+0.05 -> 0.113003 | C6: =RAND()*0.15+0.05 -> 0.055981183 | D6: =RAND()*0.15+0.05 -> 0.17517791 | E6: =RAND()*0.15+0.05 -> 0.17749746 | F6: =RAND()*0.15+0.05 -> 0.12114588 | G6: =RAND()*0.15+0.05 -> 0.052009451 | H6: =RAND()*0.15+0.05 -> 0.12835181 | I6: =RAND()*0.15+0.05 -> 0.18483236 | ... K6: =RAND()*0.15+0.05 -> 0.13230399
A7: Grants Management System | B7: =RAND()*0.15+0.05 -> 0.16385096 | C7: =RAND()*0.15+0.05 -> 0.063501682 | D7: =RAND()*0.15+0.05 -> 0.084027992 | E7: =RAND()*0.15+0.05 -> 0.18809892 | F7: =RAND()*0.15+0.05 -> 0.11895984 | G7: =RAND()*0.15+0.05 -> 0.15218252 | H7: =RAND()*0.15+0.05 -> 0.18882591 | I7: =RAND()*0.15+0.05 -> 0.099134151 | ... K7: =RAND()*0.15+0.05 -> 0.1415908
A8: Payroll Adjustment Tool | B8: =RAND()*0.15+0.05 -> 0.050701814 | C8: =RAND()*0.15+0.05 -> 0.16538329 | D8: =RAND()*0.15+0.05 -> 0.093174 | E8: =RAND()*0.15+0.05 -> 0.17092664 | F8: =RAND()*0.15+0.05 -> 0.16231666 | G8: =RAND()*0.15+0.05 -> 0.072348749 | H8: =RAND()*0.15+0.05 -> 0.10564076 | I8: =RAND()*0.15+0.05 -> 0.15537019 | ... K8: =RAND()*0.15+0.05 -> 0.094855556
A9: Crime Analytics Portal | B9: =RAND()*0.15+0.05 -> 0.057433107 | C9: =RAND()*0.15+0.05 -> 0.18074231 | D9: =RAND()*0.15+0.05 -> 0.073850302 | E9: =RAND()*0.15+0.05 -> 0.1327911 | F9: =RAND()*0.15+0.05 -> 0.11951763 | G9: =RAND()*0.15+0.05 -> 0.16466385 | H9: =RAND()*0.15+0.05 -> 0.0934142 | I9: =RAND()*0.15+0.05 -> 0.1975237 | ... K9: =RAND()*0.15+0.05 -> 0.14373184
A10: Park Reservation App | B10: =RAND()*0.15+0.05 -> 0.14062084 | C10: =RAND()*0.15+0.05 -> 0.15797986 | D10: =RAND()*0.15+0.05 -> 0.054901857 | E10: =RAND()*0.15+0.05 -> 0.098644707 | F10: =RAND()*0.15+0.05 -> 0.092473467 | G10: =RAND()*0.15+0.05 -> 0.070888014 | H10: =RAND()*0.15+0.05 -> 0.10596449 | I10: =RAND()*0.15+0.05 -> 0.11973107 | ... K10: =RAND()*0.15+0.05 -> 0.086130312
A11: Zoning Map Interface | B11: =RAND()*0.15+0.05 -> 0.13393695 | C11: =RAND()*0.15+0.05 -> 0.16856863 | D11: =RAND()*0.15+0.05 -> 0.081120635 | E11: =RAND()*0.15+0.05 -> 0.067644337 | F11: =RAND()*0.15+0.05 -> 0.14598605 | G11: =RAND()*0.15+0.05 -> 0.19246952 | H11: =RAND()*0.15+0.05 -> 0.17683183 | I11: =RAND()*0.15+0.05 -> 0.075263263 | ... K11: =RAND()*0.15+0.05 -> 0.073731934
A12: Procurement Workflow Tool | B12: =RAND()*0.15+0.05 -> 0.19069971 | C12: =RAND()*0.15+0.05 -> 0.14744084 | D12: =RAND()*0.15+0.05 -> 0.15798567 | E12: =RAND()*0.15+0.05 -> 0.091259365 | F12: =RAND()*0.15+0.05 -> 0.12701302 | G12: =RAND()*0.15+0.05 -> 0.13945948 | H12: =RAND()*0.15+0.05 -> 0.086809803 | I12: =RAND()*0.15+0.05 -> 0.069284874 | ... K12: =RAND()*0.15+0.05 -> 0.073832316
A13: Vendor Risk Portal | B13: =RAND()*0.15+0.05 -> 0.12709668 | C13: =RAND()*0.15+0.05 -> 0.11465901 | D13: =RAND()*0.15+0.05 -> 0.053123324 | E13: =RAND()*0.15+0.05 -> 0.1882145 | F13: =RAND()*0.15+0.05 -> 0.10753438 | G13: =RAND()*0.15+0.05 -> 0.064301179 | H13: =RAND()*0.15+0.05 -> 0.081766263 | I13: =RAND()*0.15+0.05 -> 0.1685845 | ... K13: =RAND()*0.15+0.05 -> 0.1513104
... A101: Digital Records Archive B | B101: =RAND()*0.15+0.05 -> 0.095345913 | C101: =RAND()*0.15+0.05 -> 0.060988634 | D101: =RAND()*0.15+0.05 -> 0.16661127 | E101: =RAND()*0.15+0.05 -> 0.070764125 | F101: =RAND()*0.15+0.05 -> 0.072856316 | G101: =RAND()*0.15+0.05 -> 0.067205713 | H101: =RAND()*0.15+0.05 -> 0.072222244 | I101: =RAND()*0.15+0.05 -> 0.17263007 | ... K101: =RAND()*0.15+0.05 -> 0.06598193

Sheet AI Automation Potential
A1: App Name | B1: Requirements Gathering & Analysis | C1: Solution Design & Architecture | D1: Stakeholder Alignment & Change Mgmt | E1: Configuration & Customization | F1: Integration Development | G1: Testing & Quality Assurance | H1: Documentation & Knowledge Transfer | I1: Project Management & Governance | J1: Training & Enablement | K1: Ongoing Support & Optimization
A2: Building Permit Processing System | B2: =RAND()*0.2+0.1 -> 0.28102725 | C2: =RAND()*0.2+0.1 -> 0.10913932 | D2: =RAND()*0.2+0.1 -> 0.12654052 | E2: =RAND()*0.2+0.1 -> 0.19927263 | F2: =RAND()*0.2+0.1 -> 0.14114036 | G2: =RAND()*0.2+0.1 -> 0.23611971 | H2: =RAND()*0.2+0.1 -> 0.10644707 | I2: =RAND()*0.2+0.1 -> 0.24642849 | ... K2: =RAND()*0.2+0.1 -> 0.14272054
A3: Employee Training Portal | B3: =RAND()*0.2+0.1 -> 0.20033736 | C3: =RAND()*0.2+0.1 -> 0.13426005 | D3: =RAND()*0.2+0.1 -> 0.13487045 | E3: =RAND()*0.2+0.1 -> 0.14946231 | F3: =RAND()*0.2+0.1 -> 0.29055207 | G3: =RAND()*0.2+0.1 -> 0.18225004 | H3: =RAND()*0.2+0.1 -> 0.26773689 | I3: =RAND()*0.2+0.1 -> 0.27331007 | ... K3: =RAND()*0.2+0.1 -> 0.13593223
A4: Fleet Maintenance Dashboard | B4: =RAND()*0.2+0.1 -> 0.14921029 | C4: =RAND()*0.2+0.1 -> 0.19156212 | D4: =RAND()*0.2+0.1 -> 0.15474373 | E4: =RAND()*0.2+0.1 -> 0.27200526 | F4: =RAND()*0.2+0.1 -> 0.21517843 | G4: =RAND()*0.2+0.1 -> 0.27674705 | H4: =RAND()*0.2+0.1 -> 0.18262814 | I4: =RAND()*0.2+0.1 -> 0.21509402 | ... K4: =RAND()*0.2+0.1 -> 0.16620829
A5: 311 Case Routing App | B5: =RAND()*0.2+0.1 -> 0.29730516 | C5: =RAND()*0.2+0.1 -> 0.2381538 | D5: =RAND()*0.2+0.1 -> 0.29262256 | E5: =RAND()*0.2+0.1 -> 0.17963326 | F5: =RAND()*0.2+0.1 -> 0.24993133 | G5: =RAND()*0.2+0.1 -> 0.27552994 | H5: =RAND()*0.2+0.1 -> 0.1183868 | I5: =RAND()*0.2+0.1 -> 0.14913321 | ... K5: =RAND()*0.2+0.1 -> 0.29572095
A6: Public Health Inspection Tracker | B6: =RAND()*0.2+0.1 -> 0.28956189 | C6: =RAND()*0.2+0.1 -> 0.22892272 | D6: =RAND()*0.2+0.1 -> 0.19096839 | E6: =RAND()*0.2+0.1 -> 0.20411652 | F6: =RAND()*0.2+0.1 -> 0.24668714 | G6: =RAND()*0.2+0.1 -> 0.21517378 | H6: =RAND()*0.2+0.1 -> 0.15763047 | I6: =RAND()*0.2+0.1 -> 0.19222179 | ... K6: =RAND()*0.2+0.1 -> 0.1986193
A7: Grants Management System | B7: =RAND()*0.2+0.1 -> 0.22083294 | C7: =RAND()*0.2+0.1 -> 0.15944151 | D7: =RAND()*0.2+0.1 -> 0.25815676 | E7: =RAND()*0.2+0.1 -> 0.21000956 | F7: =RAND()*0.2+0.1 -> 0.18876606 | G7: =RAND()*0.2+0.1 -> 0.26925574 | H7: =RAND()*0.2+0.1 -> 0.11725944 | I7: =RAND()*0.2+0.1 -> 0.22549584 | ... K7: =RAND()*0.2+0.1 -> 0.29630677
A8: Payroll Adjustment Tool | B8: =RAND()*0.2+0.1 -> 0.20943964 | C8: =RAND()*0.2+0.1 -> 0.24194637 | D8: =RAND()*0.2+0.1 -> 0.27928625 | E8: =RAND()*0.2+0.1 -> 0.22627291 | F8: =RAND()*0.2+0.1 -> 0.25785824 | G8: =RAND()*0.2+0.1 -> 0.20844658 | H8: =RAND()*0.2+0.1 -> 0.15636911 | I8: =RAND()*0.2+0.1 -> 0.22646445 | ... K8: =RAND()*0.2+0.1 -> 0.13439907
A9: Crime Analytics Portal | B9: =RAND()*0.2+0.1 -> 0.21963877 | C9: =RAND()*0.2+0.1 -> 0.17949215 | D9: =RAND()*0.2+0.1 -> 0.1000108 | E9: =RAND()*0.2+0.1 -> 0.18462598 | F9: =RAND()*0.2+0.1 -> 0.11482394 | G9: =RAND()*0.2+0.1 -> 0.18062132 | H9: =RAND()*0.2+0.1 -> 0.26317332 | I9: =RAND()*0.2+0.1 -> 0.25407529 | ... K9: =RAND()*0.2+0.1 -> 0.29286051
A10: Park Reservation App | B10: =RAND()*0.2+0.1 -> 0.1116546 | C10: =RAND()*0.2+0.1 -> 0.27241018 | D10: =RAND()*0.2+0.1 -> 0.28735795 | E10: =RAND()*0.2+0.1 -> 0.27911355 | F10: =RAND()*0.2+0.1 -> 0.14500222 | G10: =RAND()*0.2+0.1 -> 0.16041224 | H10: =RAND()*0.2+0.1 -> 0.19110427 | I10: =RAND()*0.2+0.1 -> 0.23737064 | ... K10: =RAND()*0.2+0.1 -> 0.23104768
A11: Zoning Map Interface | B11: =RAND()*0.2+0.1 -> 0.22748409 | C11: =RAND()*0.2+0.1 -> 0.14251182 | D11: =RAND()*0.2+0.1 -> 0.15944168 | E11: =RAND()*0.2+0.1 -> 0.29703019 | F11: =RAND()*0.2+0.1 -> 0.29723285 | G11: =RAND()*0.2+0.1 -> 0.22967478 | H11: =RAND()*0.2+0.1 -> 0.24234372 | I11: =RAND()*0.2+0.1 -> 0.12574047 | ... K11: =RAND()*0.2+0.1 -> 0.22599565
A12: Procurement Workflow Tool | B12: =RAND()*0.2+0.1 -> 0.24052026 | C12: =RAND()*0.2+0.1 -> 0.11150644 | D12: =RAND()*0.2+0.1 -> 0.17394186 | E12: =RAND()*0.2+0.1 -> 0.1758647 | F12: =RAND()*0.2+0.1 -> 0.13336521 | G12: =RAND()*0.2+0.1 -> 0.21931126 | H12: =RAND()*0.2+0.1 -> 0.25744209 | I12: =RAND()*0.2+0.1 -> 0.21135172 | ... K12: =RAND()*0.2+0.1 -> 0.26614676
A13: Vendor Risk Portal | B13: =RAND()*0.2+0.1 -> 0.24045772 | C13: =RAND()*0.2+0.1 -> 0.23297028 | D13: =RAND()*0.2+0.1 -> 0.24517986 | E13: =RAND()*0.2+0.1 -> 0.2970792 | F13: =RAND()*0.2+0.1 -> 0.28340181 | G13: =RAND()*0.2+0.1 -> 0.16900997 | H13: =RAND()*0.2+0.1 -> 0.15409287 | I13: =RAND()*0.2+0.1 -> 0.17194011 | ... K13: =RAND()*0.2+0.1 -> 0.16081568
... A101: Digital Records Archive B | B101: =RAND()*0.2+0.1 -> 0.26615184 | C101: =RAND()*0.2+0.1 -> 0.20515502 | D101: =RAND()*0.2+0.1 -> 0.1779534 | E101: =RAND()*0.2+0.1 -> 0.28673986 | F101: =RAND()*0.2+0.1 -> 0.15729487 | G101: =RAND()*0.2+0.1 -> 0.17021178 | H101: =RAND()*0.2+0.1 -> 0.25285579 | I101: =RAND()*0.2+0.1 -> 0.26466538 | ... K101: =RAND()*0.2+0.1 -> 0.26629145

Sheet IA Structure
A1: IA Component Lvl1 | B1: IA Component Lowest
A2: Soft | B2: Requirements Gathering & Analysis
A3: Soft | B3: Solution Design & Architecture
A4: Soft | B4: Stakeholder Alignment & Change Mgmt
A5: Hard | B5: Configuration & Customization
A6: Hard | B6: Integration Development
A7: Hard | B7: Testing & Quality Assurance
A8: Soft | B8: Documentation & Knowledge Transfer
A9: Soft | B9: Project Management & Governance
A10: Soft | B10: Training & Enablement
A11: Hard | B11: Ongoing Support & Optimization
